{
  "skippableComposables": 5,
  "restartableComposables": 7,
  "readonlyComposables": 0,
  "totalComposables": 7,
  "restartGroups": 7,
  "totalGroups": 14,
  "staticArguments": 9,
  "certainArguments": 0,
  "knownStableArguments": 107,
  "knownUnstableArguments": 0,
  "unknownStableArguments": 0,
  "totalArguments": 107,
  "markedStableClasses": 1,
  "inferredStableClasses": 9,
  "inferredUnstableClasses": 10,
  "inferredUncertainClasses": 1,
  "effectivelyStableClasses": 10,
  "totalClasses": 21,
  "memoizedLambdas": 4,
  "singletonLambdas": 0,
  "singletonComposableLambdas": 3,
  "composableLambdas": 3,
  "totalLambdas": 6
}
